gallia/__init__.py
gallia/cli/__init__.py
gallia/cli/cursed_hr.py
gallia/cli/gallia.py
gallia/cli/hr.py
gallia/cli/netzteil.py
gallia/command/__init__.py
gallia/command/base.py
gallia/command/config.py
gallia/command/uds.py
gallia/commands/__init__.py
gallia/commands/discover/__init__.py
gallia/commands/discover/doip.py
gallia/commands/discover/find_xcp.py
gallia/commands/discover/hsfz.py
gallia/commands/discover/isotp.py
gallia/commands/fuzz/__init__.py
gallia/commands/fuzz/uds/__init__.py
gallia/commands/fuzz/uds/pdu.py
gallia/commands/primitive/__init__.py
gallia/commands/primitive/generic/__init__.py
gallia/commands/primitive/generic/pdu.py
gallia/commands/primitive/uds/__init__.py
gallia/commands/primitive/uds/dddi.py
gallia/commands/primitive/uds/dtc.py
gallia/commands/primitive/uds/ecu_reset.py
gallia/commands/primitive/uds/iocbi.py
gallia/commands/primitive/uds/pdu.py
gallia/commands/primitive/uds/ping.py
gallia/commands/primitive/uds/rdbi.py
gallia/commands/primitive/uds/rmba.py
gallia/commands/primitive/uds/rtcl.py
gallia/commands/primitive/uds/vin.py
gallia/commands/primitive/uds/wdbi.py
gallia/commands/primitive/uds/wmba.py
gallia/commands/primitive/xcp.py
gallia/commands/scan/__init__.py
gallia/commands/scan/uds/__init__.py
gallia/commands/scan/uds/identifiers.py
gallia/commands/scan/uds/memory.py
gallia/commands/scan/uds/reset.py
gallia/commands/scan/uds/sa_dump_seeds.py
gallia/commands/scan/uds/services.py
gallia/commands/scan/uds/sessions.py
gallia/commands/script/__init__.py
gallia/commands/script/flexray.py
gallia/commands/script/rerun.py
gallia/commands/script/vecu.py
gallia/config.py
gallia/db/__init__.py
gallia/db/handler.py
gallia/db/log.py
gallia/dumpcap.py
gallia/exitcodes.py
gallia/log.py
gallia/net.py
gallia/plugins/__init__.py
gallia/plugins/plugin.py
gallia/plugins/uds.py
gallia/plugins/xcp.py
gallia/power_supply/__init__.py
gallia/power_supply/base.py
gallia/power_supply/devices/__init__.py
gallia/power_supply/devices/rnd.py
gallia-2.0.2.dist-info/WHEEL
gallia-2.0.2.dist-info/entry_points.txt
gallia-2.0.2.dist-info/METADATA
gallia-2.0.2.dist-info/RECORD
