Metadata-Version: 2.3
Name: gallia
Version: 2.0.2
Summary: Extendable Pentesting Framework
Author: AISEC Pentesting Team
Classifier: Development Status :: 4 - Beta
Classifier: License :: OSI Approved :: Apache Software License
Classifier: Topic :: Security
Classifier: Operating System :: Microsoft :: Windows
Classifier: Operating System :: POSIX :: Linux
Classifier: Programming Language :: Python :: 3.11
Classifier: Programming Language :: Python :: 3.12
Classifier: Programming Language :: Python :: 3.13
Classifier: Programming Language :: Python :: 3.14
Requires-Dist: aiosqlite>=0.18
Requires-Dist: argcomplete>=2,<4
Requires-Dist: boltons>=24.1.0
Requires-Dist: construct>=2.10,<3.0
Requires-Dist: platformdirs>=2.6,<5.0
Requires-Dist: pydantic>=2.12,<3.0
Requires-Dist: tabulate>=0.9
Requires-Dist: zstandard>=0.19 ; python_full_version < '3.14'
Requires-Dist: more-itertools>=10.3.0,<11.0.0 ; python_full_version < '3.12' and sys_platform == 'win32'
Requires-Dist: construct-typing>=0.5.2,<0.7.0 ; extra == 'dev'
Requires-Dist: mypy>=1.0,<2.0 ; extra == 'dev'
Requires-Dist: pylsp-mypy>=0.6,<0.8 ; extra == 'dev'
Requires-Dist: pylsp-rope>=0.1,<0.2 ; extra == 'dev'
Requires-Dist: pytest>=7.1,<10.0 ; extra == 'dev'
Requires-Dist: pytest-asyncio>=0.20,<1.4 ; extra == 'dev'
Requires-Dist: pytest-cov>=4,<8 ; extra == 'dev'
Requires-Dist: python-lsp-server>=1.5,<2.0 ; extra == 'dev'
Requires-Dist: reuse>=4.0,<7.0 ; extra == 'dev'
Requires-Dist: ruff>=0.9.0 ; extra == 'dev'
Requires-Dist: rust-just>=1.38.0 ; extra == 'dev'
Requires-Dist: ty>=0.0.1a29 ; extra == 'dev'
Requires-Dist: types-tabulate>=0.9,<0.10 ; extra == 'dev'
Requires-Dist: types-boltons>=25.0.0.20250919 ; extra == 'dev'
Maintainer: Stefan Tatschner, Tobias Specht
Maintainer-email: Stefan Tatschner <stefan.tatschner@aisec.fraunhofer.de>, Tobias Specht <tobias.specht@aisec.fraunhofer.de>
Requires-Python: >=3.11, <3.15
Project-URL: Bug Tracker, https://github.com/Fraunhofer-AISEC/gallia/issues
Project-URL: Documentation, https://github.com/Fraunhofer-AISEC/gallia
Project-URL: Repository, https://github.com/Fraunhofer-AISEC/gallia
Provides-Extra: dev
